paczekfiller/__init__.py
paczekfiller/cli.py
paczekfiller/paczekfiller.py
paczekfiller-0.1.4.data/scripts/paczek
paczekfiller-0.1.4.dist-info/LICENSE
paczekfiller-0.1.4.dist-info/METADATA
paczekfiller-0.1.4.dist-info/WHEEL
paczekfiller-0.1.4.dist-info/entry_points.txt
paczekfiller-0.1.4.dist-info/top_level.txt
paczekfiller-0.1.4.dist-info/RECORD
