Metadata-Version: 2.1
Name: paczekfiller
Version: 0.1.4
Summary: Pączek filler - simple script for filling out single template files
Home-page: https://github.com/kr1surb4n/paczekfiller
Author: Kris Urbanski
Author-email: kris@whereibend.space
License: MIT
Platform: UNKNOWN
Classifier: Development Status :: 2 - Pre-Alpha
Classifier: License :: OSI Approved :: MIT License
Classifier: Programming Language :: Python :: 3.5
Classifier: Programming Language :: Python :: 3.6
Requires-Dist: Click
Requires-Dist: Jinja2
Provides-Extra: fzf
Requires-Dist: fzf ; extra == 'fzf'
